Workbook

Sheet 主要经济技术指标表
A1: 序号 | B1: 项目名称 | C1: 单位 | D1: 指标
A2: 一 | B2: 生产规模 | C2: 104t/a | D2: 10.5
A3: 二 | B3: 产品方案
A4: 1 | B4: 己二腈 | C4: t/a | D4: =产品销售收入和税金估算!D2 -> 107777.89
A5: 2 | B5: 1-亚氨基-2-氰基环戊烷 | C5: t/a | D5: =产品销售收入和税金估算!D4 -> 17472.952
A6: 3 | B6: 己二腈二聚物 | C6: t/a | D6: =产品销售收入和税金估算!D3 -> 5120.5137
A7: 三 | B7: 年操作时间 | C7: h | D7: 8000
A8: 四 | B8: 主要原材料、辅助原料用量
A9: 1 | B9: 己二酸 | C9: t/a | D9: =直接材料费用表!C3 -> 178561.9
A10: 2 | B10: 氨 | C10: t/a | D10: =直接材料费用表!C4 -> 47681.06
A11: 3 | B11: 磷酸催化剂 | C11: t/a | D11: =直接材料费用表!C5 -> 0.96
A12: 4 | B12: 硫酸铝 | C12: t/a | D12: =直接材料费用表!C7 -> 0.72
A13: 5 | B13: 硅藻土（载体） | C13: t/a | D13: =直接材料费用表!C8 -> 0.216
A14: 4 | B14: 工艺软水 | C14: t/a | D14: =直接材料费用表!C6 -> 22160.402
A15: 五 | B15: 共用动力消耗
A16: 1 | B16: 电 | C16: kW·h | D16: =直接材料费用表!D14 -> 62679987
A17: 2 | B17: 0.25MPa低压蒸汽 | C17: t | D17: =直接材料费用表!D15 -> 801274.59
A18: 3 | B18: 4MPa中压蒸汽 | C18: t | D18: =直接材料费用表!D16 -> 4282326.8
A19: 4 | B19: 20℃冷却水 | C19: t | D19: =直接材料费用表!D17 -> 15706407
A20: 5 | B20: ﹣25℃冷冻盐水 | C20: t | D20: =直接材料费用表!D18 -> 35826.937
A21: 6 | B21: 三氟甲烷 | C21: t | D21: =直接材料费用表!D13 -> 34628.882
A22: 7 | B22: 氮气 | C22: Nm3 | D22: =直接材料费用表!D19 -> 62800
A23: 8 | B23: 仪表空气 | C23: Nm3 | D23: =直接材料费用表!D20 -> 48000
A24: 9 | B24: 烟道气 | C24: t | D24: =能耗分析!D12 -> 1151570.9
A25: 六 | B25: 三废排放
A26: 1 | B26: 废水 | C26: t/a | D26: 124829.52
A27: 2 | B27: 废气 | C27: m3/h | D27: 150
A28: 3 | B28: 废固 | C28: t/a | D28: 8.72
A29: 七 | B29: 全厂定员 | C29: 人 | D29: 52
A30: 八 | B30: 总占地面积 | C30: m2 | D30: 103315
A31: 九 | B31: 综合能耗总量 | C31: t标煤/a | D31: =能耗分析!H30*0.001 -> 648039.27
A32: 十 | B32: 单位产品综合能耗 | C32: t标煤/t产品 | D32: =能耗分析!G30*0.0001 -> 0.49707184
A33: 十一 | B33: 工程项目总投资 | C33: 万元 | D33: =建设投资估算表!C69 -> 42897.264
A34: 1 | B34: 建设投资 | C34: 万元 | D34: =建设投资估算表!C62 -> 35738.45
A35: 2 | B35: 流动资金 | C35: 万元 | D35: =建设投资估算表!C68 -> 5360.7675
A36: 3 | B36: 建设期利息 | C36: 万元 | D36: =建设投资估算表!C67 -> 1798.0465
A37: 十二 | B37: 年总销售收入 | C37: 万元 | D37: =产品销售收入和税金估算!D10 -> 522126.73
A38: 十三 | B38: 年总成本 | C38: 万元 | D38: =产品成本汇总表!C52 -> 455372.97
A39: 十四 | B39: 年利润总额 | C39: 万元 | D39: =财务报表!C6 -> 57058.891
A40: 十五 | B40: 年销售额税金及附加 | C40: 万元 | D40: =财务报表!C5 -> 9694.8661
A41: 十六 | B41: 财务评价指标
A42: 1 | B42: 投资利润率 | C42: % | D42: =财务报表!B71 -> 133.01289
A43: 2 | B43: 投资利税率 | C43: % | D43: =财务报表!B72 -> 155.61309
A44: 3 | B44: 资本金净利润率 | C44: % | D44: =财务报表!B73 -> 119.74265
A45: 4 | B45: 财务净现值 | C45: 万元 | D45: =财务报表!E92 -> 196029.36
A46: 5 | B46: 财务内部收益率 | C46: % | D46: =财务报表!B97*100 -> 89.097
A47: 十七 | B47: 清偿能力指标
A48: 1 | B48: 人民币借款偿还期 | C48: 年 | D48: 6

Sheet 直接材料费用表
A1: 原材料及辅助材料费用表
A2: 项目 | B2: 名称 | C2: 数量（t/a） | D2: 单价（元/吨） | E2: 总费用（万元/年）
A3: 主要原料 | B3: 己二酸 | C3: =22320.2378*8000*0.001 -> 178561.9 | D3: 8900 | E3: =D3*C3*0.0001 -> 158920.09
B4: 氨 | C4: =5960.13250864294*8000*0.001 -> 47681.06 | D4: 2800 | E4: =D4*C4*0.0001 -> 13350.697
A5: 辅助原料 | B5: 磷酸 | C5: =0.16*6 -> 0.96 | D5: 6800 | E5: =D5*C5*0.0001 -> 0.6528
B6: 工艺软水 | C6: =(0.596072858150109+67.1622+2702.292)*8000*0.001 -> 22160.402 | D6: 10 | E6: =D6*C6*0.0001 -> 22.160402
B7: 硫酸铝 | C7: =0.12*6 -> 0.72 | D7: 1350 | E7: =D7*C7*0.0001 -> 0.0972 | F7: 重庆长鹏化工
B8: 硅藻土（载体） | C8: =6*0.036 -> 0.216 | D8: 3200 | E8: =D8*C8*0.0001 -> 0.06912 | F8: 武汉卡诺斯科技
A9: 合计 | E9: =SUM(E3:E8) -> 172293.77
A11: 公用工程名称 | B11: 单位 | C11: 消耗 | E11: 单价（元/吨） | F11: 总费用（万元/年）
C12: 小时耗量 | D12: 年耗量
A13: 三氟甲烷 | B13: t/a | C13: 4.3286102 | D13: =C13*8000 -> 34628.882 | E13: 120 | F13: =E13*D13*0.0001 -> 415.54658
A14: 电 | B14: kW·h/a | C14: 7834.9984 | D14: =C14*8000 -> 62679987 | E14: 0.75 | F14: =E14*D14*0.0001 -> 4700.999
A15: 0.25MPa低压蒸汽 | B15: t/a | C15: 100.15932 | D15: =C15*8000 -> 801274.59 | E15: 200 | F15: =E15*D15*0.0001 -> 16025.492
A16: 4MPa中压蒸汽 | B16: t/a | C16: 535.29086 | D16: =C16*8000 -> 4282326.8 | E16: 265 | F16: =E16*D16*0.0001 -> 113481.66
A17: 20℃冷却水 | B17: t/a | C17: 1963.3008 | D17: =C17*8000 -> 15706407 | E17: 0.5 | F17: =E17*D17*0.0001 -> 785.32033
A18: -25℃冷冻盐水 | B18: t/a | C18: 4.4783672 | D18: =C18*8000 -> 35826.937 | E18: 30 | F18: =E18*D18*0.0001 -> 107.48081
A19: 氮气 | B19: Nm3/a | C19: 7.85 | D19: =C19*8000 -> 62800 | E19: 0.2 | F19: =E19*D19*0.0001 -> 1.256 | H19: 燃料气的成本计算：
A20: 仪表空气 | B20: Nm3/a | C20: 6 | D20: =C20*8000 -> 48000 | E20: 0.12 | F20: =E20*D20*0.0001 -> 0.576 | H20: 1吨煤产生6690立方米燃料气 | I20: 800元/吨
A21: 燃料气 | B21: t/a | C21: 143.94636 | D21: =C21*8000 -> 1151570.9 | E21: 119.58 | F21: =E21*D21*0.001 -> 137704.84 | H21: 6.69吨 | I21: =800/6.69 -> 119.58146
A22: 合计（万元/年） | F22: =SUM(F13:F21) -> 273223.18
A23: 总计直接材料费用（万元/年） | F23: =F22+E9 -> 445516.95
A36: 工业增加值 | B36: =B35-B36+B37 -> 0
A37: 工业总产值
A38: 工业中间投入
A39: 本期应交增税值

Sheet 产品销售收入和税金估算
A1: 序号 | B1: 产品 | C1: 规格（wt%） | D1: 产量（吨/年） | E1: 单位售价（元/吨） | F1: 总售价（万元/年）
A2: 1 | B2: 己二腈 | C2: 99.99 | D2: =13472.2356422869*8000*0.001 -> 107777.89 | E2: 35000 | F2: =E2*D2*0.0001 -> 377222.6
A3: 2 | B3: 己二腈二聚物 | C3: 99 | D3: =640.064211784675*8000*0.001 -> 5120.5137 | E3: 10000 | F3: =E3*D3*0.0001 -> 5120.5137
A4: 3 | B4: ICCP | C4: 99.1 | D4: =2184.11899444088*8000*0.001 -> 17472.952 | E4: 80000 | F4: =E4*D4*0.0001 -> 139783.62
A5: 总计（万元/年） | F5: =SUM(F2:F4) -> 522126.73
C7: 产品总产量 | D7: =D4+D3+D2 -> 130371.35
A8: 税金估算表
A9: 序号 | B9: 项目 | C9: 税率（%） | D9: 税金（万元）
B10: 产品销售收入 | D10: =F5 -> 522126.73
B11: 销项税额 | C11: 13 | D11: =D10*C11/(100+C11) -> 60067.677
B12: 产品总成本 | D12: =产品成本汇总表!C52 -> 455372.97
B13: 购入原材料和动力费 | D13: =直接材料费用表!F23 -> 445516.95
B14: 进项税额 | C14: 13 | D14: =D13*C14/(100+C14) -> 51254.162
A15: 1 | B15: 增值税 | C15: 13 | D15: =D11-D14 -> 8813.5146
A16: 2 | B16: 城市维护建设费 | C16: 7 | D16: =D15*C16*0.01 -> 616.94602
A17: 3 | B17: 教育附加税 | C17: 3 | D17: =D15*C17*0.01 -> 264.40544
B18: 销售税金及附加 | D18: =D15+D16+D17 -> 9694.8661
A19: 4 | B19: 企业所得税 | C19: 25 | D19: =C19*0.01*(D10-D12) -> 16688.439

Sheet 工资和生活用水费
A1: 部门 | C1: 人数/班 | D1: 班次 | E1: 人数小计/人 | F1: 个人工资 | G1: 总工资（万元/年）
A2: 行政办公楼 | B2: 总经理 | C2: 1 | D2: 1 | E2: =D2*C2 -> 1 | F2: 20 | G2: =F2*E2 -> 20
B3: 总工程师 | C3: 1 | D3: 1 | E3: =D3*C3 -> 1 | F3: 15 | G3: =F3*E3 -> 15
A4: 办公室 | C4: 2 | D4: 1 | E4: =D4*C4 -> 2 | F4: 12 | G4: =F4*E4 -> 24
A5: 财务部 | C5: 2 | D5: 1 | E5: =D5*C5 -> 2 | F5: 10 | G5: =F5*E5 -> 20
A6: 生产部 | B6: 主任 | C6: 2 | D6: 1 | E6: =D6*C6 -> 2 | F6: 11 | G6: =F6*E6 -> 22
B7: 员工 | C7: 6 | D7: 4 | E7: =D7*C7 -> 24 | F7: 9 | G7: =F7*E7 -> 216
A8: 应急处理中心 | B8: 部长 | C8: 1 | D8: 1 | E8: =D8*C8 -> 1 | F8: 11 | G8: =F8*E8 -> 11
B9: 员工 | C9: 4 | D9: 1 | E9: =D9*C9 -> 4 | F9: 9 | G9: =F9*E9 -> 36
A10: 保卫处 | C10: 4 | D10: 1 | E10: =D10*C10 -> 4 | F10: 8 | G10: =F10*E10 -> 32
A11: 化验中心 | C11: 2 | D11: 1 | E11: =D11*C11 -> 2 | F11: 9 | G11: =F11*E11 -> 18
A12: 市场部 | B12: 采购部 | C12: 2 | D12: 1 | E12: =D12*C12 -> 2 | F12: 10 | G12: =F12*E12 -> 20
B13: 销售部 | C13: 2 | D13: 1 | E13: =D13*C13 -> 2 | F13: 10 | G13: =F13*E13 -> 20
A14: 仪修机修车间 | C14: 2 | D14: 1 | E14: =D14*C14 -> 2 | F14: 9 | G14: =F14*E14 -> 18
A15: 后勤部 | C15: 3 | D15: 1 | E15: =D15*C15 -> 3 | F15: 8 | G15: =F15*E15 -> 24
A16: 总计 | G16: =SUM(G2:G15) -> 496
E17: =SUM(E2:E15) -> 52
A18: 项目 | B18: 单位（L/天） | C18: 总人数（人） | D18: 生活用水消耗量（吨） | E18: 单价（元/吨） | F18: 年用水费（万元/年）
A19: 生活用水 | B19: 200 | C19: =E17 -> 52 | D19: =B19*C19*300/1000 -> 3120 | E19: 2.53 | F19: =E19*D19*0.0001 -> 0.78936
B21: 序号 | C21: 福利名称 | D21: 占工资总额比例（%） | E21: 总计（万元/年）
B22: 1 | C22: 养老保险金 | D22: 14 | E22: =D22*0.01*G16 -> 69.44
B23: 2 | C23: 失业保险金 | D23: 2 | E23: =D23*0.01*G16 -> 9.92
B24: 3 | C24: 医疗保险金 | D24: 11.5 | E24: =D24*0.01*G16 -> 57.04
B25: 4 | C25: 生育保险金 | D25: 1.2 | E25: =D25*0.01*G16 -> 5.952
B26: 人工费总计（万元/年） | E26: =SUM(E22:E25,G16) -> 638.352

Sheet 设备费价格明细
A1: 塔设备价格表 | I1: 主要设备购置费用
A2: 设备位号 | B2: 名称 | C2: 材料 | D2: 重量/t | E2: 数量 | F2: 价格（万元）
A3: T0101 | B3: AA、酰胺分离塔 | C3: S30408 | D3: 25.1184 | E3: 1 | F3: =48000*0.0001*D3 -> 120.56832 | I3: 编号 | J3: 设备名称 | K3: 价格（万元）
A4: T0102 | B4: AA分离塔 | C4: S30408 | D4: 14.5668 | E4: 1 | F4: =48000*0.0001*D4 -> 69.92064 | I4: 1 | J4: 塔设备 | K4: =F10 -> 435.62928
A5: T0301 | B5: 粗产物精馏塔 | C5: S30408 | D5: 18.6235 | E5: 1 | F5: =48000*0.0001*D5 -> 89.3928 | I5: 2 | J5: 反应器 | K5: =F22 -> 799.68
A6: T0302 | B6: 热泵精馏塔 | C6: S30408 | D6: 5.9671 | E6: 1 | F6: =48000*0.0001*D6 -> 28.64208 | I6: 3 | J6: 气液分离器 | K6: =G33 -> 1081.9772
A7: T0303 | B7: ICCP精馏塔1 | C7: S30408 | D7: 9.5487 | E7: 1 | F7: =48000*0.0001*D7 -> 45.83376 | I7: 4 | J7: 换热器 | K7: =I62 -> 420.36243
A8: T0304 | B8: ICCP精馏塔2 | C8: S30408 | D8: 13.2367 | E8: 1 | F8: =48000*0.0001*D8 -> 63.53616 | I8: 5 | J8: 压缩机 | K8: =H72 -> 542.4
A9: T0305 | B9: 2ADN精馏塔 | C9: S30408 | D9: 3.6949 | E9: 1 | F9: =48000*0.0001*D9 -> 17.73552 | I9: 6 | J9: 储罐 | K9: =J79 -> 968.91
A10: 合计 | F10: =SUM(F3:F9) -> 435.62928 | I10: 7 | J10: 回流罐、分流罐、缓冲罐 | K10: =G103 -> 1080.338
I11: 8 | J11: 泵 | K11: =H136 -> 19.06
I12: 总计 | K12: =SUM(K4:K11) -> 5348.357
A14: 反应器价格表
A15: 设备位号 | B15: 名称 | C15: 材料 | D15: 重量/t | E15: 数量 | F15: 价格（万元）
A16: R0101 | B16: AA混合器 | C16: S30408 | D16: 13.51 | E16: 1 | F16: =D16*48000*0.0001 -> 64.848
A17: R0102 | B17: AA胺化反应器1 | C17: S30408 | D17: 41.11 | E17: 1 | F17: =D17*48000*0.0001 -> 197.328
A18: R0103 | B18: AA胺化反应器2 | C18: S30408 | D18: 41.11 | E18: 1 | F18: =D18*48000*0.0001 -> 197.328
A19: R0104 | B19: AA胺化反应器3 | C19: S30408 | D19: 41.11 | E19: 1 | F19: =D19*48000*0.0001 -> 197.328
A20: R0105 | B20: 酰胺脱水反应器 | C20: S30408 | D20: 27.53 | E20: 1 | F20: =D20*48000*0.0001 -> 132.144
A21: R0201 | B21: 粗氨气、水反应器 | C21: S30408 | D21: 2.23 | E21: 1 | F21: =D21*48000*0.0001 -> 10.704
A22: 合计 | F22: =SUM(F16:F21) -> 799.68
A27: 气液分离器价格表
A28: 设备位号 | B28: 名称 | C28: 类型 | D28: 材料 | E28: 重量/kg | F28: 数量 | G28: 价格(万元）
A29: V0103 | B29: 中间产物气液分离罐1 | C29: 立式丝网分离器 | D29: S30408 | E29: 2207.98 | F29: 1 | G29: 10.598
A30: V0104 | B30: 中间产物气液分离罐2 | C30: 立式丝网分离器 | D30: S30408 | E30: 284.95 | F30: 1 | G30: 1.36776
A31: V0202 | B31: 氨气闪蒸罐 | C31: 立式丝网分离器 | D31: S30408 | E31: 221533.4 | F31: 1 | G31: 1063.3603
A32: V0107 | B32: 粗产物气液分离罐 | C32: 立式丝网分离器 | D32: S30408 | E32: 1385.66 | F32: 1 | G32: 6.651168
A33: 合计 | G33: =SUM(G29:G32) -> 1081.9772
A38: 换热器价格表
A39: 设备位号 | B39: 换热器名称 | C39: 型号 | D39: 传热面积/m2 | E39: 换热管/板数量 | F39: 管程材料 | G39: 壳程材料 | H39: 数量 | I39: 总价（万元）
A40: E0101 | B40: 氨气、AND换热器 | C40: BEM600-0.33/0.088-55.8-6/25-1I | D40: 55.8 | E40: 269 | F40: 16Mn | G40: Q345R | H40: 1 | I40: =7.85*0.0001*22000*(PI()*0.025*K40*E40*0.0025+PI()*J40*K40*0.025) -> 10.355981 | J40: 0.6 | K40: 6
A41: E0102 | B41: 中间产物换热器 | C41: BEM500-0.33/0.33-90.2-6/19-2I | D41: 90.2 | E41: 256 | F41: 16Mn | G41: Q345R | H41: 1 | I41: =7.85*0.0001*22000*(PI()*0.019*6*256*0.002+PI()*0.5*6*0.025) -> 7.2359215
A42: E0103 | B42: 中间产物冷却器 | C42: BEU500-0.33/0.33-96.8-6/19-1I | D42: 96.8 | E42: 275 | F42: 16Mn | G42: Q345R | H42: 1 | I42: =7.85*0.0001*22000*(PI()*0.019*K42*E42*0.002+PI()*J42*K42*0.025) -> 7.4709555 | J42: 0.5 | K42: 6
A43: E0104 | B43: 中间产物加热器 | C43: BEU700-0.33/0.134-93.8-3/19-4I | D43: 93.8 | E43: 542 | F43: 16Mn | G43: Q345R | H43: 1 | I43: =7.85*0.0001*22000*(PI()*0.019*K43*E43*0.002+PI()*J43*K43*0.025) -> 6.2007303 | J43: 0.7 | K43: 3
A44: E0110 | B44: 废水冷却器2 | C44: BEM273-0.0123/0.111-5.4-1.5/19-1I | D44: 5.4 | E44: 65 | F44: 16Mn | G44: Q345R | H44: 1 | I44: =7.85*0.0001*22000*(PI()*0.019*K44*E44*0.002+PI()*J44*K44*0.025) -> 0.75645459 | J44: 0.273 | K44: 1.5
A45: E0303 | B45: 热泵精馏换热器 | C45: BEM1600-0.253/0.11-1687.2-9/19-4I | D45: 1687.2 | E45: 3176 | F45: 16Mn | G45: Q345R | H45: 1 | I45: =7.85*0.0001*22000*(PI()*0.019*K45*E45*0.002+PI()*J45*K45*0.025) -> 78.463588 | J45: 1.6 | K45: 9
A46: E0304 | B46: 粗AND冷却器1 | C46: BEM1300-0.08/0.275-557.6-4.5/25-1I | D46: 557.6 | E46: 2123 | F46: 16Mn | G46: Q345R | H46: 1 | I46: =7.85*0.0001*22000*(PI()*0.025*K46*E46*0.0025+PI()*J46*K46*0.025) -> 40.330342 | J46: 1.3 | K46: 4.5
A47: E0108 | B47: T0102冷凝器 | C47: BEM500-0..33/0.121-31.2-2/19-1I | D47: 31.2 | E47: 275 | F47: 16Mn | G47: Q345R | H47: 1 | I47: =7.85*0.0001*22000*(PI()*0.019*K47*E47*0.002+PI()*J47*K47*0.025) -> 2.4903185 | J47: 0.5 | K47: 2
A48: E0109 | B48: T0102再沸器 | C48: BKU800-0.55/0.33-138.0-3/19-1I | D48: 138 | E48: 797 | F48: 16Mn | G48: Q345R | H48: 1 | I48: =7.85*0.0001*22000*(PI()*0.019*K48*E48*0.002+PI()*J48*K48*0.025) -> 8.1848468 | J48: 0.8 | K48: 3
A49: E0105 | B49: T0101冷凝器 | C49: BEM900-0.11/0.121-171-3/19-2I | D49: 171 | E49: 988 | F49: 16Mn | G49: Q345R | H49: 1 | I49: =7.85*0.0001*22000*(PI()*0.019*K49*E49*0.002+PI()*J49*K49*0.025) -> 9.7731166 | J49: 0.9 | K49: 3
A50: E0106 | B50: T0101再沸器 | C50: BEM900-0.11/0.33-355.3-6/19-1I | D50: 355.3 | E50: 1009 | F50: 16Mn | G50: Q345R | H50: 1 | I50: =7.85*0.0001*22000*(PI()*0.019*K50*E50*0.002+PI()*J50*K50*0.025) -> 19.806008 | J50: 0.9 | K50: 6
A51: E0302 | B51: T0301冷凝器 | C51: BEM600-0.056/0.88-109.3-4.5/19-2I | D51: 109.3 | E51: 416 | F51: 16Mn | G51: Q345R | H51: 1 | I51: =7.85*0.0001*22000*(PI()*0.019*K51*E51*0.002+PI()*J51*K51*0.025) -> 7.5217385 | J51: 0.6 | K51: 4.5
A52: E0301 | B52: T0301再沸器 | C52: BEM1500-0.121/0.134-1556-9/19-2I | D52: 1556 | E52: 2929 | F52: 16Mn | G52: Q345R | H52: 1 | I52: =7.85*0.0001*22000*(PI()*0.019*K52*E52*0.002+PI()*J52*K52*0.025) -> 72.659681 | J52: 1.5 | K52: 9
A53: E0305 | B53: T0303冷凝器 | C53: BEM500-0.011/0.121-67.2-4.5/19-2I | D53: 67.2 | E53: 256 | F53: 16Mn | G53: Q345R | H53: 1 | I53: =7.85*0.0001*22000*(PI()*0.019*K53*E53*0.002+PI()*J53*K53*0.025) -> 5.4269412 | J53: 0.5 | K53: 4.5
A54: E0306 | B54: T0303再沸器 | C54: BKU400-0.121/0.023-18.6-2/19-2I | D54: 18.6 | E54: 164 | F54: 16Mn | G54: Q345R | H54: 1 | I54: =7.85*0.0001*22000*(PI()*0.019*K54*E54*0.002+PI()*J54*K54*0.025) -> 1.7613442 | J54: 0.4 | K54: 2
A55: E0307 | B55: T0304冷凝器 | C55: BEM800-0.55/0.33-138.0-3/19-4I | D55: 189.8 | E55: 722 | F55: 16Mn | G55: Q345R | H55: 1 | I55: =7.85*0.0001*22000*(PI()*0.019*K55*E55*0.002+PI()*J55*K55*0.025) -> 7.720964 | J55: 0.8 | K55: 3
A56: E0308 | B56: T0304再沸器 | C56: BKU900-0.23/0.88-113.8-2.5/25-1I | D56: 113.8 | E56: 605 | F56: 16Mn | G56: Q345R | H56: 1 | I56: =7.85*0.0001*22000*(PI()*0.025*K56*E56*0.0025+PI()*J56*K56*0.025) -> 8.1806827 | J56: 0.9 | K56: 2.5
A57: E0309 | B57: T0305冷凝器 | C57: BEM273-0.0123/0.111-5.4-1.5/19-1I | D57: 5.4 | E57: 65 | F57: 16Mn | G57: Q345R | H57: 1 | I57: =7.85*0.0001*22000*(PI()*0.019*K57*E57*0.002+PI()*J57*K57*0.025) -> 0.75645459 | J57: 0.273 | K57: 1.5
A58: E0310 | B58: T0305再沸器 | C58: BEM273-0.0123/0.134-11.3-3/19-1I | D58: 11.3 | E58: 65 | F58: 16Mn | G58: Q345R | H58: 1 | I58: =7.85*0.0001*22000*(PI()*0.019*K58*E58*0.002+PI()*J58*K58*0.025) -> 1.5129092 | J58: 0.273 | K58: 3
A59: E0201 | B59: T0201冷凝器 | C59: BEM1900-0.33/0.111-2424-9/19-4I | D59: 2424 | E59: 4566 | F59: 16Mn | G59: Q345R | H59: 1 | I59: =7.85*0.0001*22000*(PI()*0.019*K59*E59*0.002+PI()*J59*K59*0.025) -> 107.91771 | J59: 1.9 | K59: 9
A60: E0202 | B60: T0201再沸器 | C60: BEM800-0.55/0.134-209.3-4.5/19-1I | D60: 209.3 | E60: 797 | F60: 16Mn | G60: Q345R | H60: 1 | I60: =7.85*0.0001*22000*(PI()*0.019*K60*E60*0.002+PI()*J60*K60*0.025) -> 12.27727 | J60: 0.8 | K60: 4.5
A61: E0107 | B61: 废水冷却器1 | C61: BEM219-0.11/0.11-17.7-9/25-1I | D61: 17.7 | E61: 29 | F61: 16Mn | G61: Q345R | H61: 1 | I61: =7.85*0.0001*22000*(PI()*0.025*K61*E61*0.0025+PI()*J61*K61*0.025) -> 3.5584698 | J61: 0.219 | K61: 9
A62: 合计 | I62: =SUM(I40:I61) -> 420.36243
A64: 压缩机价格表
A65: 设备位号 | B65: 名称 | C65: 类型 | D65: 型号 | E65: 材质 | F65: 重量/t | G65: 数量 | H65: 价格（万元）
A66: C0202 | B66: 循环氨气压缩机 | C66: 离心式 | D66: DAC800 | E66: S30408 | F66: 43 | G66: 1 | H66: =48000*0.0001*F66 -> 206.4
A67: C0201 | B67: 粗氨气压缩机 | C67: 离心式 | D67: DAC400 | E67: S30408 | F67: 22 | G67: 1 | H67: =48000*0.0001*F67 -> 105.6
A68: C0301 | B68: 粗AND压缩机 | C68: 离心式 | D68: DAC400 | E68: S30408 | F68: 22 | G68: 1 | H68: =48000*0.0001*F68 -> 105.6
A69: C0101 | B69: 废水压缩机1 | C69: 离心式 | D69: DAC300 | E69: S30408 | F69: 17 | G69: 1 | H69: =48000*0.0001*F69 -> 81.6
A70: C0102 | B70: 废水压缩机2 | C70: 离心式 | D70: DAC50 | E70: S30408 | F70: 4.5 | G70: 1 | H70: =48000*0.0001*F70 -> 21.6
A71: C0401 | B71: 液氨压缩机 | C71: 离心式 | D71: DAC50 | E71: S30408 | F71: 4.5 | G71: 1 | H71: =48000*0.0001*F71 -> 21.6
A72: 合计 | H72: =SUM(H66:H71) -> 542.4
A74: 储罐价格表
A75: 设备位号 | B75: 名称 | C75: 类型 | D75: 公称容积/m3 | E75: 材料 | F75: 保护层 | G75: 总质量/t | H75: 数量 | I75: 造价(万元） | J75: 总价（万元）
A76: V0401 | B76: 液氨球型储罐 | C76: 钢制球形储罐 | D76: 2000 | E76: Q370R | F76: 不锈钢薄板 | G76: 310 | H76: 1 | I76: 422 | J76: 432
A77: V0403A/B | B77: ADN储罐 | C77: 立式圆筒形内浮顶容器 | D77: 3000 | E77: Q235-A | F77: 不锈钢薄板 | G77: 89.485 | H77: 2 | I77: =20000*0.0001*G77 -> 178.97 | J77: =I77*H77 -> 357.94
A78: V0404 | B78: 废水储罐 | C78: 立式圆筒形内浮顶容器 | D78: 3000 | E78: Q235-A | F78: 不锈钢薄板 | G78: 89.485 | H78: 1 | I78: =20000*0.0001*G78 -> 178.97 | J78: =H78*I78 -> 178.97
A79: 合计 | J79: =SUM(J76:J78) -> 968.91
A83: 回流罐、分流罐、缓冲罐价格表
A84: 设备位号 | B84: 名称 | C84: 类型 | D84: 材料 | E84: 总质量/kg | F84: 数量 | G84: 价格（万元）
A85: V0101 | B85: 氨气混合罐 | C85: 立式圆筒形内浮顶容器 | D85: S30408 | E85: 60950 | F85: 1 | G85: =22000*0.0001*E85*0.001 -> 134.09
A86: V0201 | B86: 粗氨气缓冲罐 | C86: 立式圆筒形内浮顶容器 | D86: S30408 | E86: 89485 | F86: 1 | G86: =22000*0.0001*E86*0.001 -> 196.867
A87: V0105 | B87: 粗氨气混合罐 | C87: 立式圆筒形内浮顶容器 | D87: S30408 | E87: 60950 | F87: 1 | G87: =22000*0.0001*E87*0.001 -> 134.09
A88: V0102 | B88: 汽包 | C88: 立式圆筒形内浮顶容器 | D88: S30408 | E88: 89485 | F88: 1 | G88: =22000*0.0001*E88*0.001 -> 196.867
A89: V0108 | B89: 废水缓冲罐1 | C89: 卧式椭圆形封头容器 | D89: Q235-A | E89: 640 | F89: 1 | G89: =48000*0.0001*E89*0.001 -> 3.072
A90: V0110 | B90: 废水缓冲罐2 | C90: 卧式椭圆形封头容器 | D90: Q235-A | E90: 640 | F90: 1 | G90: =48000*0.0001*E90*0.001 -> 3.072
A91: V0203 | B91: 氨气缓冲罐 | C91: 立式圆筒形内浮顶容器 | D91: S30408 | E91: 60950 | F91: 1 | G91: =22000*0.0001*E91*0.001 -> 134.09
A92: V0306 | B92: 精制ICCP混合罐 | C92: 卧式椭圆形封头容器 | D92: S30408 | E92: 6550 | F92: 1 | G92: =48000*0.0001*E92*0.001 -> 31.44
A93: V0402 | B93: 氨气缓冲罐 | C93: 立式圆筒形内浮顶容器 | D93: S30408 | E93: 60950 | F93: 1 | G93: =22000*0.0001*E93*0.001 -> 134.09
A94: V0302 | B94: AND分离罐1 | C94: 立式圆筒形内浮顶容器 | D94: S30408 | E94: 12620 | F94: 1 | G94: =22000*0.0001*E94*0.001 -> 27.764
A95: V0303 | B95: AND分离罐2 | C95: 卧式椭圆形封头容器 | D95: S30408 | E95: 6550 | F95: 1 | G95: =48000*0.0001*E95*0.001 -> 31.44
A96: V0109 | B96: T0102回流罐 | C96: 立式圆筒形内浮顶容器 | D96: S30408 | E96: 19280 | F96: 1 | G96: =22000*0.0001*E96*0.001 -> 42.416
A97: V0106 | B97: T0101回流罐 | C97: 卧式椭圆形封头容器 | D97: S30408 | E97: 640 | F97: 1 | G97: =48000*0.0001*E97*0.001 -> 3.072
A98: V0301 | B98: T0301回流罐 | C98: 卧式椭圆形封头容器 | D98: S30408 | E98: 290 | F98: 1 | G98: =48000*0.0001*E98*0.001 -> 1.392
A99: V0202 | B99: T0201回流罐 | C99: 卧式椭圆形封头容器 | D99: S30408 | E99: 290 | F99: 1 | G99: =48000*0.0001*E99*0.001 -> 1.392
A100: V0307 | B100: T0305回流罐 | C100: 卧式椭圆形封头容器 | D100: S30408 | E100: 290 | F100: 1 | G100: =48000*0.0001*E100*0.001 -> 1.392
A101: V0304 | B101: T0303回流罐 | C101: 卧式椭圆形封头容器 | D101: S30408 | E101: 500 | F101: 1 | G101: =48000*0.0001*E101*0.001 -> 2.4
A102: V0305 | B102: T0304回流罐 | C102: 卧式椭圆形封头容器 | D102: S30408 | E102: 290 | F102: 1 | G102: =48000*0.0001*E102*0.001 -> 1.392
A103: 合计 | G103: =SUM(G85:G102) -> 1080.338
A110: 泵价格表
A111: 设备位号 | B111: 名称 | C111: 型号 | D111: 类型 | E111: 材质 | F111: 造价（万元） | G111: 数量 | H111: 总价（万元）
A112: P0101A/B | B112: AA输送泵 | C112: 80D-12 | D112: 离心泵 | E112: S30408 | F112: 0.33 | G112: 1 | H112: =F112 -> 0.33
A113: P0102A/B | B113: 汽包蒸汽输送泵1 | C113: IL200-150-250 | D113: 离心泵 | E113: S30408 | F113: 2.75 | G113: 1 | H113: =F113 -> 2.75
A114: P0103A/B | B114: 汽包蒸汽输送泵2 | C114: IL150-125-250 | D114: 离心泵 | E114: S30408 | F114: 2.45 | G114: 1 | H114: =F114 -> 2.45
A115: P0104A/B | B115: 汽包蒸汽输送泵3 | C115: 300S19A | D115: 离心泵 | E115: S30408 | F115: 1.95 | G115: 1 | H115: =F115 -> 1.95
A116: P0105A/B | B116: 汽包蒸汽输送泵4 | C116: XA150/40B | D116: 离心泵 | E116: S30408 | F116: 0.22 | G116: 1 | H116: =F116 -> 0.22
A117: P0106A/B | B117: T0101回流泵 | C117: IX50-32-125A | D117: 离心泵 | E117: S30408 | F117: 0.83 | G117: 2 | H117: =F117 -> 0.83
A118: P0107A/B | B118: 酰胺输送泵 | C118: XA40/13H | D118: 离心泵 | E118: S30408 | F118: 0.21 | G118: 1 | H118: =F118 -> 0.21
A119: P0108A/B | B119: 粗ADN输送泵 | C119: IX180-65-100 | D119: 离心泵 | E119: S30408 | F119: 1.95 | G119: 1 | H119: =F119 -> 1.95
A120: P0109A/B | B120: T0102回流泵 | C120: IX165-50-125 | D120: 离心泵 | E120: S30408 | F120: 1.55 | G120: 1 | H120: =F120 -> 1.55
...

Sheet 设备购置和安装费
A1: 工业设备费 | C1: 万元 | D1: =设备费价格明细!K12 -> 5348.357
A3: 设备购置一览表
A4: 编号 | B4: 名称 | C4: 费率（%） | D4: 价格（万元)
A5: 1 | B5: 工艺设备费 | C5: 100 | D5: =D1 -> 5348.357
A6: 2 | B6: 设备内部填充费 | C6: 20 | D6: =$D$1*C6*0.01 -> 1069.6714
A7: 3 | B7: 工艺管道及防腐保温工程费 | C7: 36 | D7: =$D$1*C7*0.01 -> 1925.4085
A8: 4 | B8: 仪表控制费 | C8: 14 | D8: =$D$1*C8*0.01 -> 748.76997
A9: 5 | B9: 电动、变电配电、电讯设备 | C9: 12 | D9: =$D$1*C9*0.01 -> 641.80283
A10: 6 | B10: 生产工具费 | C10: 2.5 | D10: =$D$1*C10*0.01 -> 133.70892
A11: 7 | B11: 备品备件购置费 | C11: 6 | D11: =$D$1*C11*0.01 -> 320.90142
A12: 8 | B12: 设备运杂费 | C12: 4 | D12: =$D$1*C12*0.01 -> 213.93428
A13: 9 | B13: 公用工程设备购置费 | C13: 30 | D13: =$D$1*C13*0.01 -> 1604.5071 | E13: 小计
A14: 10 | B14: 车辆购置添加费 | C14: 20 | D14: =$D$1*C14*0.01 -> 1069.6714 | E14: =SUM(D13:D14) -> 2674.1785
A15: 总计（万元） | D15: =SUM(D5:D14) -> 13076.733
A17: 安装费用一览表
A18: 编号 | B18: 设备名称 | C18: 安装因子 | D18: 原价（万元） | E18: 价格（万元）
A19: 1 | B19: 塔设备 | C19: 0.4 | D19: =设备费价格明细!K4 -> 435.62928 | E19: =D19*C19 -> 174.25171
A20: 2 | B20: 反应器 | C20: 0.3 | D20: =设备费价格明细!K5 -> 799.68 | E20: =D20*C20 -> 239.904
A21: 3 | B21: 气液分离器 | C21: 0.3 | D21: =设备费价格明细!K6 -> 1081.9772 | E21: =D21*C21 -> 324.59317
A22: 4 | B22: 换热器 | C22: 0.3 | D22: =设备费价格明细!K7 -> 420.36243 | E22: =D22*C22 -> 126.10873
A23: 5 | B23: 压缩机 | C23: 0.2 | D23: =设备费价格明细!K8 -> 542.4 | E23: =D23*C23 -> 108.48
A24: 6 | B24: 泵 | C24: 0.2 | D24: =设备费价格明细!K11 -> 19.06 | E24: =D24*C24 -> 3.812
A25: 7 | B25: 工艺管道 | C25: 0.4 | D25: =D7 -> 1925.4085 | E25: =D25*C25 -> 770.1634
A26: 8 | B26: 仪表及自控系统 | C26: 0.2 | D26: =D8 -> 748.76997 | E26: =D26*C26 -> 149.75399
A27: 9 | B27: 其他设备 | C27: 0.2 | D27: =D9+D10+D11+D12+D13+D14 -> 3984.5259 | E27: =D27*C27 -> 796.90519
A28: 总计 | E28: =SUM(E19:E27) -> 2693.9722

Sheet 建设投资估算表
A1: 主要设备购置费用 | C1: 万元 | D1: =设备购置和安装费!D15 -> 13076.733
A3: 直接费用一览表
A4: 编号 | B4: 名称 | C4: 费率（%） | D4: 设备总费用（万元） | E4: 价格（万元）
A5: 1 | B5: 土建工程 | C5: 40 | D5: =D1 -> 13076.733 | E5: =D5*C5*0.01 -> 5230.6931
A6: 2 | B6: 场地建设 | C6: 20 | D6: =D1 -> 13076.733 | E6: =D6*C6*0.01 -> 2615.3466
A7: 总计（万元） | E7: =SUM(E5:E6) -> 7846.0397
A9: 间接费用一览表
A10: 编号 | B10: 名称 | C10: 费率（%） | D10: 基数 | E10: 价格（万元）
A11: 1 | B11: 间接费用 | C11: 10 | D11: =E7 -> 7846.0397 | E11: =D11*C11*0.01 -> 784.60397
A14: 税金一览表
A15: 编号 | B15: 名称 | C15: 费率（%） | D15: 基数 | E15: 价格（万元）
A16: 1 | B16: 营业税 | C16: 3 | D16: =E7+E11 -> 8630.6436 | E16: =D16*C16*0.01 -> 258.91931
A17: 2 | B17: 城市建设维护税 | C17: 7 | D17: =E16 -> 258.91931 | E17: =D17*C17*0.01 -> 18.124352
A18: 3 | B18: 教育附加税 | C18: 3 | D18: =E16 -> 258.91931 | E18: =D18*C18*0.01 -> 7.7675793
A19: 总计（万元） | E19: =SUM(E16:E18) -> 284.81124
A21: 建筑工程费用一览表
A22: 编号 | B22: 项目 | C22: 价格（万元）
A23: 1 | B23: 直接费用 | C23: =E7 -> 7846.0397
A24: 2 | B24: 间接费用 | C24: =E11 -> 784.60397
A25: 3 | B25: 税金 | C25: =E19 -> 284.81124
A26: 合计 | C26: =SUM(C23:C25) -> 8915.4549
A28: 固定资产投资费用汇总一览表
A29: 编号 | B29: 名称 | C29: 价格（万元）
A30: 1 | B30: 工程设备费 | C30: =D1 -> 13076.733
A31: 2 | B31: 建筑工程费 | C31: =C26 -> 8915.4549
A32: 3 | B32: 安装工程费 | C32: =设备购置和安装费!E28 -> 2693.9722
A33: 合计 | C33: =SUM(C30:C32) -> 24686.16
A35: 无形资产费用
A36: 编号 | B36: 名称 | C36: 设计用地（万㎡） | D36: 单价（万元/㎡） | E36: 价格（万元）
A37: 1 | B37: 工程设备费 | C37: 10.3315 | D37: 0.05625 | E37: =D37*C37*10000 -> 5811.4688
A38: 2 | B38: 技术转让费 | C38: - | D38: 200 | E38: 100
A40: 递延资产费用
A41: 编号 | B41: 名称 | C41: 费率（%） | D41: 基数 | E41: 价格（万元）
A42: 1 | B42: 建设单位管理费 | C42: 0.8 | D42: =C33 -> 24686.16 | E42: =D42*C42*0.01 -> 197.48928
A43: 2 | B43: 装置联合启动调试费 | C43: 1 | D43: =D42 -> 24686.16 | E43: =D43*C43*0.01 -> 246.8616
A44: 3 | B44: 研究试验费 | C44: - | D44: - | E44: 100
A45: 4 | B45: 城市基础设施配套费 | C45: - | D45: - | E45: 50
A47: 编号 | B47: 名称 | C47: 人数 | D47: 费用（元/人） | E47: 其他费用（万元） | F47: 总费用（万元）
A48: 1 | B48: 生产准备费 | C48: 52 | D48: 14000 | E48: 45 | F48: =D48*C48/10000+E48 -> 117.8
A49: 2 | B49: 办公及生活家居购置费 | C49: 52 | D49: 1000 | E49: 0 | F49: =D49*C49/10000+E49 -> 5.2
A50: 合计（万元） | F50: =SUM(F48:F49,E42:E45) -> 717.35088
A52: 建设投资估算表
A53: 编号 | B53: 项目 | C53: 价格（万元）
A54: 1 | B54: 固定资产 | C54: =C33 -> 24686.16
A55: 2 | B55: 无形资产 | C55: =E37+E38 -> 5911.4688
A56: 3 | B56: 递延资产 | C56: =F50+SUM(E42:E45) -> 1311.7018
A57: 4 | B57: 预备费用 | C57: =SUM(C54:C56)*0.12 -> 3829.1196
A58: 建设投资合计 | C58: =SUM(C54:C57) -> 35738.45
A60: 项目总投资汇总表
A61: 序号 | B61: 项目 | C61: 价格（万元）
A62: 1 | B62: 建设投资 | C62: =C58 -> 35738.45
A63: 1.1 | B63: 固定资产 | C63: =C54 -> 24686.16
A64: 1.2 | B64: 无形资产 | C64: =C55 -> 5911.4688
A65: 1.3 | B65: 递延资产 | C65: =C56 -> 1311.7018
A66: 1.4 | B66: 预备费用 | C66: =C57 -> 3829.1196
A67: 2 | B67: 建设期利息 | C67: =建设期贷款利息!C14-建设期贷款利息!C10 -> 1798.0465
A68: 3 | B68: 流动资金 | C68: =建设期贷款利息!G19 -> 5360.7675
A69: 合计 | C69: =SUM(C62,C67:C68) -> 42897.264

Sheet 建设期贷款利息
A1: 2023年中国人民银行贷款利率
A2: 期限 | B2: 年利率/%
A3: 一年以内（含一年） | B3: 4.35
A4: 一至五年（含五年） | B4: 4.75
A5: 五年以上 | B5: 4.9
A7: 建设期利息估算表（人民币单位：万元）
A8: 序号 | B8: 项目 | C8: 年份
C9: 1 | D9: 2 | E9: 3 | F9: 4 | G9: 5 | H9: 6 | I9: 7
A10: 1 | B10: 借款额 | C10: 10000 | D10: =C12-C13 -> 10245 | E10: =D12-D13 -> 8747.005 | F10: =E12-E13 -> 7175.6082 | G10: =F12-F13 -> 5527.213 | H10: =G12-G13 -> 3798.0465 | I10: =H12-H13 -> 1984.1508
A11: 2 | B11: 借款利息 | C11: =C10/2*0.049 -> 245 | D11: =D10*0.049 -> 502.005 | E11: =E10*0.049 -> 428.60324 | F11: =F10*0.049 -> 351.6048 | G11: =G10*0.049 -> 270.83344 | H11: =H10*0.049 -> 186.10428 | I11: =I10*0.049 -> 97.223388
A12: 3 | B12: 借款本息和 | C12: =C10+C11 -> 10245 | D12: =D11+D10 -> 10747.005 | E12: =E11+E10 -> 9175.6082 | F12: =F11+F10 -> 7527.213 | G12: =G11+G10 -> 5798.0465 | H12: =H11+H10 -> 3984.1508 | I12: =I11+I10 -> 2081.3742
A13: 4 | B13: 还款金额 | C13: 0 | D13: 2000 | E13: =D13 -> 2000 | F13: =E13 -> 2000 | G13: =F13 -> 2000 | H13: =G13 -> 2000 | I13: =I12 -> 2081.3742
A14: 建设期借款本息和 | C14: =SUM(C10,C11:G11) -> 11798.046
A15: 建设期贷款总利息 | C15: =SUM(C11:G11) -> 1798.0465
A16: 流动资金
A17: 项目 | B17: 金额（万元/月） | D17: 流动资金估算表
A18: 应收账款 | B18: =产品成本汇总表!C55/12 -> 37657.698 | D18: 编号 | E18: 名称 | F18: 费率（%） | G18: 价格（万元）
A19: 外购原材料 | B19: =直接材料费用表!E9/12 -> 14357.814 | D19: 1 | E19: 流动资金 | F19: 15 | G19: =(建设投资估算表!C62)*(建设期贷款利息!F19)*0.01 -> 5360.7675
A20: 外购燃料和动力 | B20: =直接材料费用表!F22/12 -> 22768.598
A21: 在制品费 | B21: =B19+B20+产品成本汇总表!C51/12+工资和生活用水费!E26/12 -> 37206.059
A22: 制成品费 | B22: =B18-B21 -> 451.63894
A23: 存货 | B23: =B19+B20+B21+B22 -> 74784.111
A24: 现金 | B24: =工资和生活用水费!E26/12 -> 53.196
A25: 应付账款 | B25: =B19+B20 -> 37126.412
A26: 流动资产 | B26: =B18+B23+B24 -> 112495
A27: 流动资金额 | B27: =B26-B25 -> 75368.593
A29: 项目 | B29: 周转天数 | C29: 年周转次数 | D29: 年份
D30: 4 | E30: 5 | F30: 6 | G30: 7
A31: 生产负荷 | D31: 1 | E31: 1 | F31: 1 | G31: 1
A32: 流动资产 | D32: =G19 -> 5360.7675 | E32: =D32 -> 5360.7675 | F32: =E32 -> 5360.7675 | G32: =F32 -> 5360.7675
A33: 应收账款 | B33: 30 | C33: 12 | D33: =B18 -> 37657.698 | E33: =D33 -> 37657.698 | F33: =E33 -> 37657.698 | G33: =F33 -> 37657.698
A34: 存货 | D34: =B23 -> 74784.111 | E34: =D34 -> 74784.111 | F34: =E34 -> 74784.111 | G34: =F34 -> 74784.111
A35: 原材料 | B35: 30 | C35: 12 | D35: =B19 -> 14357.814 | E35: =D35 -> 14357.814 | F35: =E35 -> 14357.814 | G35: =F35 -> 14357.814
A36: 燃料 | B36: 30 | C36: 12 | D36: =B20 -> 22768.598 | E36: =D36 -> 22768.598 | F36: =E36 -> 22768.598 | G36: =F36 -> 22768.598
A37: 现金 | B37: 30 | C37: 12 | D37: =B24 -> 53.196 | E37: =D37 -> 53.196 | F37: =E37 -> 53.196 | G37: =F37 -> 53.196
A38: 流动资金 | D38: =B27 -> 75368.593 | E38: =D38 -> 75368.593 | F38: =E38 -> 75368.593 | G38: =F38 -> 75368.593
A39: 流动资金本年增加额 | D39: 0 | E39: =D39 -> 0 | F39: 0 | G39: 0
A40: 流动资金借款利率 | C40: 0.0435
A41: 流贷借款 | D41: =C14 -> 11798.046 | E41: =D41 -> 11798.046 | F41: =E41 -> 11798.046 | G41: =F41 -> 11798.046
A42: 流贷借款利息 | D42: =D13 -> 2000 | E42: =D42 -> 2000 | F42: =E42 -> 2000 | G42: =F42 -> 2000

Sheet 产品成本汇总表
A1: 折旧费
A2: 名称 | B2: 原值（万元） | C2: 折旧年限（年） | D2: 年折旧率 | E2: 年折旧费（万元/年)
A3: 生产设备 | B3: =设备购置和安装费!D1 -> 5348.357 | C3: 10 | D3: 0.095 | E3: =B3*D3 -> 508.09391
A4: 房屋建筑 | B4: =建设投资估算表!E7 -> 7846.0397 | C4: 20 | D4: 0.0475 | E4: =B4*D4 -> 372.68688
A5: 生产器具、工具、家具 | B5: =设备购置和安装费!D6+设备购置和安装费!D7+设备购置和安装费!D8+设备购置和安装费!D10+设备购置和安装费!D11+设备购置和安装费!D12+设备购置和安装费!D13 -> 6016.9016 | C5: 5 | D5: 0.19 | E5: =B5*D5 -> 1143.2113
A6: 电气设备 | B6: =设备购置和安装费!D9 -> 641.80283 | C6: 5 | D6: 0.19 | E6: =B6*D6 -> 121.94254
A7: 车辆 | B7: =设备购置和安装费!D14 -> 1069.6714 | C7: 5 | D7: 0.19 | E7: =B7*D7 -> 203.23756
A8: 总计 | E8: =SUM(E3:E7) -> 2349.1722
A10: 摊销费
A11: 名称 | B11: 费用（万元）
A12: 无形资产费用 | B12: =建设投资估算表!C64 -> 5911.4688
A13: 递延资产费用 | B13: =建设投资估算表!F50 -> 717.35088
A14: 总计 | B14: =SUM(B12:B13) -> 6628.8196
A15: 摊销费 | B15: =B14/14 -> 473.48712
A17: 修理费
A18: 编号 | B18: 名称 | C18: 费率（%） | D18: 基数 | E18: 价格（万元）
A19: 1 | B19: 修理费 | C19: 1.2 | D19: =B3 -> 5348.357 | E19: =D19*C19*0.01 -> 64.180283
A21: 管理费
A22: 编号 | B22: 名称 | C22: 费率（%） | D22: 基数 | E22: 价格（万元）
A23: 1 | B23: 管理费 | C23: 40 | D23: =工资和生活用水费!G16 -> 496 | E23: =D23*C23*0.01 -> 198.4
A25: 财务费
A26: 编号 | B26: 名称 | C26: 价格（万元）
A27: 1 | B27: 财务费 | C27: =建设期贷款利息!C10*0.0475*5/4 -> 593.75
A29: 销售费用
A30: 编号 | B30: 名称 | C30: 费率（%） | D30: 基数 | E30: 价格（万元）
A31: 1 | B31: 销售费用 | C31: 1 | D31: =产品销售收入和税金估算!F5 -> 522126.73 | E31: =D31*C31*0.01 -> 5221.2673
A33: 三废处理
A34: 编号 | B34: 名称 | C34: 价格（万元）
A35: 1 | B35: 废气 | C35: 5
A36: 2 | B36: 废液 | C36: =5*主要经济技术指标表!D26*0.0001 -> 62.41476
A37: 3 | B37: 废固 | C37: 250
A38: 总计（万元/年） | C38: =SUM(C35:C37) -> 317.41476
A40: 产品成本汇总表
A41: 序号 | B41: 项目 | C41: 估算成本（万元） | D41: 占生产成本比例（%）
A42: 1 | B42: 原材料及辅助费 | C42: =直接材料费用表!E9 -> 172293.77 | D42: =C42/$C$52*100 -> 37.835748
A43: 2 | B43: 燃料动力费 | C43: =直接材料费用表!F22 -> 273223.18 | D43: =C43/$C$52*100 -> 59.999867
A44: 3 | B44: 人工费 | C44: =工资和生活用水费!E26 -> 638.352 | D44: =C44/$C$52*100 -> 0.14018223
A45: 4 | B45: 折旧费 | C45: =E8 -> 2349.1722 | D45: =C45/$C$52*100 -> 0.51587871
A46: 5 | B46: 摊销费 | C46: =B15 -> 473.48712 | D46: =C46/$C$52*100 -> 0.10397787
A47: 6 | B47: 维修费 | C47: =E19 -> 64.180283 | D47: =C47/$C$52*100 -> 0.014094004
A48: 7 | B48: 管理费 | C48: =E23 -> 198.4 | D48: =C48/$C$52*100 -> 0.043568682
A49: 8 | B49: 财务费 | C49: =C27 -> 593.75 | D49: =C49/$C$52*100 -> 0.13038762
A50: 9 | B50: 销售费 | C50: =E31 -> 5221.2673 | D50: =C50/$C$52*100 -> 1.1465914
A51: 10 | B51: 其他直接支出 | C51: =C38 -> 317.41476 | D51: =C51/$C$52*100 -> 0.069704348
A52: 总计 | B52: 总成本费用 | C52: =SUM(C42:C51) -> 455372.97 | D52: 100
B53: 可变成本 | C53: =SUM(C42:C43,C50:C51) -> 451055.63 | D53: =C53/C52*100 -> 99.051911
B54: 固定成本 | C54: =SUM(C44:C49) -> 4317.3416 | D54: =C54/C52*100 -> 0.94808912
B55: 经营成本 | C55: =C52-C45-C46-C47-C49 -> 451892.38 | D55: =C55/C52*100 -> 99.235662

Sheet 财务报表
A1: 利润与利润分配表
A2: 序号 | B2: 项目 | C2: 金额（万元） | D2: 备注
A3: 1 | B3: 产品销售收入 | C3: =产品销售收入和税金估算!F5 -> 522126.73
A4: 2 | B4: 总成本费用 | C4: =产品成本汇总表!C52 -> 455372.97
A5: 3 | B5: 销售税金及附加 | C5: =产品销售收入和税金估算!D18 -> 9694.8661
A6: 4 | B6: 利润总额 | C6: =C3-C4-C5 -> 57058.891 | D6: =1-2-3
A7: 5 | B7: 所得税 | C7: =C6*0.25 -> 14264.723 | D7: 利润总额25%
A8: 6 | B8: 净利润 | C8: =C6-C7 -> 42794.168 | D8: =4-5
A9: 7 | B9: 法定盈余公积金 | C9: =C8*0.1 -> 4279.4168 | D9: 净利润10%
A10: 8 | B10: 任意盈余公积金 | C10: =C8*0.05 -> 2139.7084 | D10: 净利润5%
A11: 9 | B11: 未分配利润 | C11: =C8-C9-C10 -> 36375.043 | D11: =6-7-8
A13: 财务损益表
A14: 序号 | B14: 项目 | C14: 建设期 | D14: 投产期 | F14: 达产期
C15: 1 | D15: 2 | E15: 3 | F15: 4
B16: 生产负荷（%） | C16: 0 | D16: 70 | E16: 90 | F16: 100
A17: 一 | B17: 产品销售收入 | C17: 0 | D17: =$C$3*0.01*D16 -> 365488.71 | E17: =$C$3*0.01*E16 -> 469914.05 | F17: =$C$3*0.01*F16 -> 522126.73
A18: 二 | B18: 总成本费用 | C18: 0 | D18: =$C$4*D16*0.01 -> 318761.08 | E18: =$C$4*E16*0.01 -> 409835.67 | F18: =$C$4*F16*0.01 -> 455372.97
A19: 三 | B19: 销售税金及附加
A20: 1 | B20: 销项税额 | C20: 0 | D20: =产品销售收入和税金估算!$D$11*D16*0.01 -> 42047.374 | E20: =产品销售收入和税金估算!$D$11*E16*0.01 -> 54060.909 | F20: =产品销售收入和税金估算!$D$11*F16*0.01 -> 60067.677
B21: 进项税额 | C21: 0 | D21: =产品销售收入和税金估算!$D$14*D16*0.01 -> 35877.913 | E21: =产品销售收入和税金估算!$D$14*E16*0.01 -> 46128.746 | F21: =产品销售收入和税金估算!$D$14*F16*0.01 -> 51254.162
B22: 增值税 | C22: 0 | D22: =D20-D21 -> 6169.4602 | E22: =E20-E21 -> 7932.1632 | F22: =F20-F21 -> 8813.5146
A23: 2 | B23: 城市维护建设费 | C23: 0 | D23: =产品销售收入和税金估算!$D$16*D16*0.01 -> 431.86222 | E23: =产品销售收入和税金估算!$D$16*E16*0.01 -> 555.25142 | F23: =产品销售收入和税金估算!$D$16*F16*0.01 -> 616.94602
A24: 3 | B24: 教育附加税 | C24: 0 | D24: =产品销售收入和税金估算!$D$17*0.01*D16 -> 185.08381 | E24: =产品销售收入和税金估算!$D$17*0.01*E16 -> 237.96489 | F24: =产品销售收入和税金估算!$D$17*0.01*F16 -> 264.40544
A25: 4 | B25: 小计 | C25: 0 | D25: =SUM(D22:D24) -> 6786.4063 | E25: =SUM(E22:E24) -> 8725.3795 | F25: =SUM(F22:F24) -> 9694.8661
A26: 四 | B26: 利润总额 | C26: 0 | D26: =$C$6*0.01*D16 -> 39941.224 | E26: =$C$6*0.01*E16 -> 51353.002 | F26: =$C$6*0.01*F16 -> 57058.891
A27: 五 | B27: 所得税 | C27: 0 | D27: =$C$7*0.01*D16 -> 9985.306 | E27: =$C$7*0.01*E16 -> 12838.251 | F27: =$C$7*0.01*F16 -> 14264.723
A28: 六 | B28: 净利润 | C28: 0 | D28: =$C$8*0.01*D16 -> 29955.918 | E28: =$C$8*0.01*E16 -> 38514.752 | F28: =$C$8*0.01*F16 -> 42794.168
A30: 财务现金流量表
A31: 序号 | B31: 项目 | C31: 投产期 | G31: 达产期 | H31: 达产期 | N31: 达产期
C32: 0 | D32: 1 | E32: 2 | F32: 3 | G32: 4 | H32: 5 | I32: 6 | J32: 7 | K32: 8 | L32: 9 | M32: 10 | N32: 11 | O32: 12 | P32: 13 | Q32: 14 | R32: 15
A33: 一 | B33: 现金流入
A34: 1 | B34: 销售收入 | E34: =D17 -> 365488.71 | F34: =E17 -> 469914.05 | G34: =F17 -> 522126.73 | H34: =G34 -> 522126.73 | I34: =H34 -> 522126.73 | J34: =I34 -> 522126.73 | K34: =J34 -> 522126.73 | L34: =K34 -> 522126.73 | M34: =L34 -> 522126.73 | N34: =M34 -> 522126.73 | O34: =N34 -> 522126.73 | ... R34: =Q34 -> 522126.73
A35: 2 | B35: 回收固定资产余值
A36: 3 | B36: 回收流动资金
A37: 4 | B37: 小计 | E37: =E34 -> 365488.71 | F37: =F34 -> 469914.05 | G37: =G34 -> 522126.73 | H37: =H34 -> 522126.73 | I37: =I34 -> 522126.73 | J37: =J34 -> 522126.73 | K37: =K34 -> 522126.73 | L37: =L34 -> 522126.73 | ... R37: =R34 -> 522126.73
A38: 二 | B38: 现金流出
A39: 1 | B39: 建设期投资 | D39: =建设投资估算表!C58 -> 35738.45
A40: 2 | B40: 流动资金 | D40: =建设期贷款利息!G19 -> 5360.7675
A41: 3 | B41: 经营成本 | E41: =G41*0.7 -> 316324.67 | F41: =G41*0.9 -> 406703.14 | G41: =产品成本汇总表!C55 -> 451892.38 | H41: =G41 -> 451892.38 | I41: =H41 -> 451892.38 | J41: =I41 -> 451892.38 | K41: =J41 -> 451892.38 | L41: =K41 -> 451892.38 | M41: =L41 -> 451892.38 | N41: =M41 -> 451892.38 | O41: =N41 -> 451892.38 | ... R41: =Q41 -> 451892.38
A42: 4 | B42: 销售税金及附加 | E42: =D25 -> 6786.4063 | F42: =E25 -> 8725.3795 | G42: =F25 -> 9694.8661 | H42: =G42 -> 9694.8661 | I42: =H42 -> 9694.8661 | J42: =I42 -> 9694.8661 | K42: =J42 -> 9694.8661 | L42: =K42 -> 9694.8661 | M42: =L42 -> 9694.8661 | N42: =M42 -> 9694.8661 | O42: =N42 -> 9694.8661 | ... R42: =Q42 -> 9694.8661
A43: 5 | B43: 偿还本息 | E43: =建设期贷款利息!D13 -> 2000 | F43: =建设期贷款利息!E13 -> 2000 | G43: =建设期贷款利息!F13 -> 2000 | H43: =建设期贷款利息!G13 -> 2000 | I43: =建设期贷款利息!H13 -> 2000 | J43: =建设期贷款利息!I13 -> 2081.3742
A44: 6 | B44: 小计 | D44: =D39+D40 -> 41099.217 | E44: =SUM(E41:E43) -> 325111.07 | F44: =SUM(F41:F43) -> 417428.52 | G44: =SUM(G41:G43) -> 463587.25 | H44: =SUM(H41:H43) -> 463587.25 | I44: =SUM(I41:I43) -> 463587.25 | J44: =SUM(J41:J43) -> 463668.62 | K44: =SUM(K41:K43) -> 461587.25 | L44: =SUM(L41:L43) -> 461587.25 | ... R44: =SUM(R41:R43) -> 461587.25
A45: 三 | B45: 所得税前现金流量 | D45: =-1*D44 -> -41099.217 | E45: =E37-E44 -> 40377.637 | F45: =F37-F44 -> 52485.533 | G45: =G37-G44 -> 58539.481 | H45: =H37-H44 -> 58539.481 | I45: =I37-I44 -> 58539.481 | J45: =J37-J44 -> 58458.107 | K45: =K37-K44 -> 60539.481 | L45: =L37-L44 -> 60539.481 | ... R45: =R37-R44 -> 60539.481
A46: 四 | B46: 累计所得税前净现金流量 | D46: =D45 -> -41099.217 | E46: =D46+E45 -> -721.58088 | F46: =E46+F45 -> 51763.952 | G46: =F46+G45 -> 110303.43 | H46: =G46+H45 -> 168842.91 | I46: =H46+I45 -> 227382.39 | J46: =I46+J45 -> 285840.5 | K46: =J46+K45 -> 346379.98 | L46: =K46+L45 -> 406919.46 | ... R46: =Q46+R45 -> 770156.35
A47: 五 | B47: 所得税 | E47: =D27 -> 9985.306 | F47: =E27 -> 12838.251 | G47: =F27 -> 14264.723 | H47: =G47 -> 14264.723 | I47: =H47 -> 14264.723 | J47: =I47 -> 14264.723 | K47: =J47 -> 14264.723 | L47: =K47 -> 14264.723 | M47: =L47 -> 14264.723 | N47: =M47 -> 14264.723 | O47: =N47 -> 14264.723 | ... R47: =Q47 -> 14264.723
A48: 六 | B48: 所得税后净现金流量 | D48: =D46 -> -41099.217 | E48: =E45-E47 -> 30392.331 | F48: =F45-F47 -> 39647.282 | G48: =G45-G47 -> 44274.758 | H48: =H45-H47 -> 44274.758 | I48: =I45-I47 -> 44274.758 | J48: =J45-J47 -> 44193.384 | K48: =K45-K47 -> 46274.758 | L48: =L45-L47 -> 46274.758 | ... R48: =R45-R47 -> 46274.758
A49: 七 | B49: 累计所得税后净现金流量 | C49: 0 | D49: =D48 -> -41099.217 | E49: =D49+E48 -> -10706.887 | F49: =E49+F48 -> 28940.395 | G49: =F49+G48 -> 73215.153 | H49: =G49+H48 -> 117489.91 | I49: =H49+I48 -> 161764.67 | J49: =I49+J48 -> 205958.05 | K49: =J49+K48 -> 252232.81 | L49: =K49+L48 -> 298507.57 | ... R49: =Q49+R48 -> 576156.12
A51: 权益投资现金流量表
A52: 序号 | B52: 项目 | C52: 建设期 | E52: 投产期 | G52: 达产期 | I52: 投产期
C53: 0 | D53: 1 | E53: 2 | F53: 3 | G53: 4 | H53: 5 | I53: 6 | J53: 7 | K53: 8 | L53: 9 | M53: 10 | N53: 11 | O53: 12 | P53: 13 | Q53: 14 | R53: 15
A54: 一 | B54: 现金流入
A55: 1 | B55: 销售收入 | D55: 0 | E55: =E34 -> 365488.71 | F55: =F34 -> 469914.05 | G55: =G34 -> 522126.73 | H55: =H34 -> 522126.73 | I55: =I34 -> 522126.73 | J55: =J34 -> 522126.73 | K55: =K34 -> 522126.73 | L55: =L34 -> 522126.73 | ... R55: =R34 -> 522126.73
A56: 2 | B56: 回收固定资产余值
A57: 3 | B57: 回收流动资金
A58: 4 | B58: 小计 | E58: =E55 -> 365488.71 | F58: =F55 -> 469914.05 | G58: =G55 -> 522126.73 | H58: =H55 -> 522126.73 | I58: =I55 -> 522126.73 | J58: =J55 -> 522126.73 | K58: =K55 -> 522126.73 | L58: =L55 -> 522126.73 | ... R58: =R55 -> 522126.73
A59: 二 | B59: 现金流出
A60: 1 | B60: 建设期投资 | D60: =D39 -> 35738.45
A61: 2 | B61: 偿还本息 | E61: =E43 -> 2000 | F61: =F43 -> 2000 | G61: =G43 -> 2000 | H61: =H43 -> 2000 | I61: =I43 -> 2000 | J61: =J43 -> 2081.3742
A62: 3 | B62: 经营成本 | E62: =E41 -> 316324.67 | F62: =F41 -> 406703.14 | G62: =G41 -> 451892.38 | H62: =H41 -> 451892.38 | I62: =I41 -> 451892.38 | J62: =J41 -> 451892.38 | K62: =K41 -> 451892.38 | L62: =L41 -> 451892.38 | ... R62: =R41 -> 451892.38
A63: 4 | B63: 销售税金及附加 | E63: =E42 -> 6786.4063 | F63: =F42 -> 8725.3795 | G63: =G42 -> 9694.8661 | H63: =H42 -> 9694.8661 | I63: =I42 -> 9694.8661 | J63: =J42 -> 9694.8661 | K63: =K42 -> 9694.8661 | L63: =L42 -> 9694.8661 | ... R63: =R42 -> 9694.8661
A64: 5 | B64: 所得税 | E64: =E47 -> 9985.306 | F64: =F47 -> 12838.251 | G64: =G47 -> 14264.723 | H64: =H47 -> 14264.723 | I64: =I47 -> 14264.723 | J64: =J47 -> 14264.723 | K64: =K47 -> 14264.723 | L64: =L47 -> 14264.723 | ... R64: =R47 -> 14264.723
A65: 6 | B65: 小计 | D65: =D60 -> 35738.45 | E65: =SUM(E61:E64) -> 335096.38 | F65: =SUM(F61:F64) -> 430266.77 | G65: =SUM(G61:G64) -> 477851.97 | H65: =SUM(H61:H64) -> 477851.97 | I65: =SUM(I61:I64) -> 477851.97 | J65: =SUM(J61:J64) -> 477933.34 | K65: =SUM(K61:K64) -> 475851.97 | L65: =SUM(L61:L64) -> 475851.97 | ... R65: =SUM(R61:R64) -> 475851.97
A66: 三 | B66: 净现金流量 | D66: =-D65 -> -35738.45 | E66: =E58-E65 -> 30392.331 | F66: =F58-F65 -> 39647.282 | G66: =G58-G65 -> 44274.758 | H66: =H58-H65 -> 44274.758 | I66: =I58-I65 -> 44274.758 | J66: =J58-J65 -> 44193.384 | K66: =K58-K65 -> 46274.758 | L66: =L58-L65 -> 46274.758 | ... R66: =R58-R65 -> 46274.758
A67: 四 | B67: 累计现金流量 | C67: 0 | D67: =D66 -> -35738.45 | E67: =D67+E66 -> -5346.1193 | F67: =E67+F66 -> 34301.163 | G67: =F67+G66 -> 78575.921 | H67: =G67+H66 -> 122850.68 | I67: =H67+I66 -> 167125.44 | J67: =I67+J66 -> 211318.82 | K67: =J67+K66 -> 257593.58 | L67: =K67+L66 -> 303868.34 | ... R67: =Q67+R66 -> 581516.88
A70: 静态投资回收期 | B70: =3-1-E49/F49 -> 2.3699634
A71: 投资利润率 | B71: =F26/建设投资估算表!C69*100 -> 133.01289
A72: 投资利税率 | B72: =(产品销售收入和税金估算!D10-产品销售收入和税金估算!D12)/建设投资估算表!C69*100 -> 155.61309
A73: 资本金净利润率 | B73: =F28/D60*100 -> 119.74265
A75: 累计折现流量表
A76: 年份t | B76: (CI-CO)t | C76: (1+in*)t | D76: (CI-CO)t/(1+in*)t | E76: ∑(CI-CO)t/(1+in*)t
A77: 0 | E77: 0
A78: 1 | B78: =D66 -> -35738.45 | C78: =POWER(1.13,A78) -> 1.13 | D78: =B78/C78 -> -31626.947 | E78: =D78 -> -31626.947
A79: 2 | B79: =E66 -> 30392.331 | C79: =POWER(1.13,A79) -> 1.2769 | D79: =B79/C79 -> 23801.653 | E79: =D79+E78 -> -7825.2939
A80: 3 | B80: =F66 -> 39647.282 | C80: =POWER(1.13,A80) -> 1.442897 | D80: =B80/C80 -> 27477.555 | E80: =D80+E79 -> 19652.261
A81: 4 | B81: 29195.082 | C81: =POWER(1.13,A81) -> 1.6304736 | D81: =B81/C81 -> 17905.89 | E81: =D81+E80 -> 37558.152
A82: 5 | B82: =G66 -> 44274.758 | C82: =POWER(1.13,A82) -> 1.8424352 | D82: =B82/C82 -> 24030.565 | E82: =D82+E81 -> 61588.717
A83: 6 | B83: =H66 -> 44274.758 | C83: =POWER(1.13,A83) -> 2.0819518 | D83: =B83/C83 -> 21265.987 | E83: =D83+E82 -> 82854.703
A84: 7 | B84: =J66 -> 44193.384 | C84: =POWER(1.13,A84) -> 2.3526055 | D84: =B84/C84 -> 18784.868 | E84: =D84+E83 -> 101639.57
A85: 8 | B85: =K66 -> 46274.758 | C85: =POWER(1.13,A85) -> 2.6584442 | D85: =B85/C85 -> 17406.707 | E85: =D85+E84 -> 119046.28
A86: 9 | B86: =L66 -> 46274.758 | C86: =POWER(1.13,A86) -> 3.0040419 | D86: =B86/C86 -> 15404.165 | E86: =D86+E85 -> 134450.44
A87: 10 | B87: =B86 -> 46274.758 | C87: =POWER(1.13,A87) -> 3.3945674 | D87: =B87/C87 -> 13632.005 | E87: =D87+E86 -> 148082.45
A88: 11 | B88: =B87 -> 46274.758 | C88: =POWER(1.13,A88) -> 3.8358612 | D88: =B88/C88 -> 12063.721 | E88: =D88+E87 -> 160146.17
A89: 12 | B89: =B88 -> 46274.758 | C89: =POWER(1.13,A89) -> 4.3345231 | D89: =B89/C89 -> 10675.859 | E89: =D89+E88 -> 170822.03
A90: 13 | B90: =B89 -> 46274.758 | C90: =POWER(1.13,A90) -> 4.8980111 | D90: =B90/C90 -> 9447.6629 | E90: =D90+E89 -> 180269.69
A91: 14 | B91: =B90 -> 46274.758 | C91: =POWER(1.13,A91) -> 5.5347525 | D91: =B91/C91 -> 8360.7637 | E91: =D91+E90 -> 188630.45
A92: 15 | B92: =B91 -> 46274.758 | C92: =POWER(1.13,A92) -> 6.2542704 | D92: =B92/C92 -> 7398.9059 | E92: =D92+E91 -> 196029.36
A94: 净现值率 | B94: =E92/建设投资估算表!C69*100 -> 456.97404
A95: 动态投资回收期 | B95: =3-1-E79/B80 -> 2.1973728
A97: FIRR | B97: 0.89097 | I97: 1.04208
A98: 年份t | B98: (CI-CO)t | C98: (1+in*)t | D98: (CI-CO)t/(1+in*)t | E98: ∑(CI-CO)t/(1+in*)t | H98: 年份t | I98: (CI-CO)t | J98: (1+in*)t | K98: (CI-CO)t/(1+in*)t | L98: ∑(CI-CO)t/(1+in*)t
A99: 1 | B99: =D48 -> -41099.217 | C99: =POWER($B$97+1,A99) -> 1.89097 | D99: =B99/C99 -> -21734.463 | E99: =D99 -> -21734.463 | H99: 1 | I99: =D66 -> -35738.45 | J99: =POWER($I$97+1,H99) -> 2.04208 | K99: =I99/J99 -> -17501.004 | L99: =K99 -> -17501.004
A100: 2 | B100: =E48 -> 30392.331 | C100: =POWER($B$97+1,A100) -> 3.5757675 | D100: =B100/C100 -> 8499.5264 | E100: =D100+E99 -> -13234.937 | H100: 2 | I100: =E66 -> 30392.331 | J100: =POWER($I$97+1,H100) -> 4.1700907 | K100: =I100/J100 -> 7288.1701 | L100: =K100+L99 -> -10212.834
A101: 3 | B101: =F48 -> 39647.282 | C101: =POWER($B$97+1,A101) -> 6.7616691 | D101: =B101/C101 -> 5863.5348 | E101: =D101+E100 -> -7371.4018 | H101: 3 | I101: =G66 -> 44274.758 | J101: =POWER($I$97+1,H101) -> 8.5156589 | K101: =I101/J101 -> 5199.217 | L101: =K101+L100 -> -5013.6168
A102: 4 | B102: =G48 -> 44274.758 | C102: =POWER($B$97+1,A102) -> 12.786114 | D102: =B102/C102 -> 3462.7221 | E102: =D102+E101 -> -3908.6797 | H102: 4 | I102: =H66 -> 44274.758 | J102: =POWER($I$97+1,H102) -> 17.389657 | K102: =I102/J102 -> 2546.0398 | L102: =K102+L101 -> -2467.577
A103: 5 | B103: =H48 -> 44274.758 | C103: =POWER($B$97+1,A103) -> 24.178157 | D103: =B103/C103 -> 1831.1883 | E103: =D103+E102 -> -2077.4914 | H103: 5 | I103: =I66 -> 44274.758 | J103: =POWER($I$97+1,H103) -> 35.51107 | K103: =I103/J103 -> 1246.7875 | L103: =K103+L102 -> -1220.7895
A104: 6 | B104: =H48 -> 44274.758 | C104: =POWER($B$97+1,A104) -> 45.72017 | D104: =B104/C104 -> 968.38569 | E104: =D104+E103 -> -1109.1057 | H104: 6 | I104: =J66 -> 44193.384 | J104: =POWER($I$97+1,H104) -> 72.516446 | K104: =I104/J104 -> 609.42567 | L104: =K104+L103 -> -611.36382
A105: 7 | B105: =B104 -> 44274.758 | C105: =POWER($B$97+1,A105) -> 86.455469 | D105: =B105/C105 -> 512.11055 | E105: =D105+E104 -> -596.99515 | H105: 7 | I105: =K66 -> 46274.758 | J105: =POWER($I$97+1,H105) -> 148.08438 | K105: =I105/J105 -> 312.48911 | L105: =K105+L104 -> -298.8747
A106: 8 | B106: =K48 -> 46274.758 | C106: =POWER($B$97+1,A106) -> 163.4847 | D106: =B106/C106 -> 283.05253 | E106: =D106+E105 -> -313.94262 | H106: 8 | I106: =L66 -> 46274.758 | J106: =POWER($I$97+1,H106) -> 302.40016 | K106: =I106/J106 -> 153.02491 | L106: =K106+L105 -> -145.84979
A107: 9 | B107: =L48 -> 46274.758 | C107: =POWER($B$97+1,A107) -> 309.14466 | D107: =B107/C107 -> 149.68642 | E107: =D107+E106 -> -164.2562 | H107: 9 | I107: =M66 -> 46274.758 | J107: =POWER($I$97+1,H107) -> 617.52532 | K107: =I107/J107 -> 74.935807 | L107: =K107+L106 -> -70.913983
A108: 10 | B108: =B107 -> 46274.758 | C108: =POWER($B$97+1,A108) -> 584.58328 | D108: =B108/C108 -> 79.158539 | E108: =D108+E107 -> -85.097659 | H108: 10 | I108: =N66 -> 46274.758 | J108: =POWER($I$97+1,H108) -> 1261.0361 | K108: =I108/J108 -> 36.695823 | L108: =K108+L107 -> -34.218159
...

Sheet 不确定分析
A1: 项目 | B1: 符号 | C1: 数量 | D1: 单位
A2: 己二腈（及副产物）年产量 | B2: Q | C2: =产品销售收入和税金估算!D7 -> 130371.35 | D2: 吨
A3: 单位产品销售收入 | B3: P | C3: =产品销售收入和税金估算!F5/C2*10000 -> 40049.192 | D3: 元/吨
A4: 年总固定成本 | B4: F | C4: =产品成本汇总表!C54 -> 4317.3416 | D4: 万元 | F4: =C4/(C3-C5-C6)*10000 -> 51152.963
A5: 单位产品可变成本 | B5: V | C5: =产品成本汇总表!C53/C2*10000 -> 34597.757 | D5: 元/吨
A6: 单位产品销售税金 | B6: m | C6: =产品销售收入和税金估算!D11/C2*10000 -> 4607.4292 | D6: 元/吨
A7: 项目产销盈亏平衡点 | B7: BEPQ | C7: =C4/(C3-C5-C6) -> 5.1152963 | D7: 万吨
A8: 产销所允许降低的最大幅度 | C8: =(C2-C7*10000)/C2*100 -> 60.763647 | D8: %
A9: 销售单价盈亏平衡点 | B9: BEPL | C9: =(C4*10000+C5*C2)/C2/(1-C6/C3) -> 39469.673 | D9: 元/吨
A10: 最大允许降低幅度 | C10: =(C3-C9)/C3*100 -> 1.4470187 | D10: % | F10: =5.12*10000/C2*100 -> 39.272432
A12: 年产销量（吨) | B12: 0 | C12: 1 | D12: 2 | E12: 3 | F12: 4 | G12: 5 | H12: 6 | I12: 7 | J12: 8 | K12: 9 | L12: 10 | M12: 0.93
A13: 销售收入（万元） | B13: =B12*25000 -> 0 | C13: =C12*C3 -> 40049.192 | D13: =D12*C3 -> 80098.384 | E13: =E12*C3 -> 120147.58 | F13: =F12*C3 -> 160196.77 | G13: =G12*C3 -> 200245.96 | H13: =H12*C3 -> 240295.15 | I13: =I12*C3 -> 280344.34 | J13: =J12*C3 -> 320393.54 | K13: =K12*C3 -> 360442.73 | L13: =L12*C3 -> 400491.92 | M13: =M12*C3 -> 37245.749
A14: 总成本（万元) | B14: =C4 -> 4317.3416 | C14: =$B$14+$C$5*C12 -> 38915.098 | D14: =$B$14+$C$5*D12 -> 73512.855 | E14: =$B$14+$C$5*E12 -> 108110.61 | F14: =$B$14+$C$5*F12 -> 142708.37 | G14: =$B$14+$C$5*G12 -> 177306.13 | H14: =$B$14+$C$5*H12 -> 211903.88 | I14: =$B$14+$C$5*I12 -> 246501.64 | J14: =$B$14+$C$5*J12 -> 281099.4 | ... M14: =$B$14+$C$5*M12 -> 36493.255
A16: 敏感性分析
A17: 变动因素 | B17: 变动幅度
B18: -0.1 | C18: -0.05 | D18: 0 | E18: 0.05 | F18: 0.1
A19: 经营成本（万元） | B19: =D19*(1+B18) -> 406703.14 | C19: =D19*(1+C18) -> 429297.76 | D19: =产品成本汇总表!C55 -> 451892.38 | E19: =D19*(1+E18) -> 474487 | F19: =E19*(1+F18) -> 521935.7
A20: 财务净现值（万元） | B20: =D20*(1+12.1%) -> 219748.91 | C20: =D20*(1+6%) -> 207791.12 | D20: =财务报表!E92 -> 196029.36 | E20: =D20*(1-6%) -> 184267.6 | F20: =D20*(1-12.2%) -> 172113.78
A22: 变动因素 | B22: 变动幅度
B23: -0.1 | C23: -0.05 | D23: 0 | E23: 0.05 | F23: 0.1
A24: 己二腈产量（吨） | B24: =D24*(1+B23) -> 97000.097 | C24: =D24*(1+C23) -> 102388.99 | D24: =产品销售收入和税金估算!D2 -> 107777.89 | E24: =D24*(1+E23) -> 113166.78 | F24: =E24*(1+F23) -> 124483.46
A25: 财务净现值（万元） | B25: =D25*(1-11.5%) -> 173485.98 | C25: =D25*(1-5.5%) -> 185247.75 | D25: =D20 -> 196029.36 | E25: =D25*(1+5.5%) -> 206810.97 | F25: =D25*(1+11.3%) -> 218180.68
A27: 变动因素 | B27: 变动幅度
B28: -0.1 | C28: -0.05 | D28: 0 | E28: 0.05 | F28: 0.1
A29: 己二腈价格（元/吨） | B29: =D29*(1+B28) -> 31500 | C29: =D29*(1+C28) -> 33250 | D29: 35000 | E29: =D29*(1+0.05) -> 36750 | F29: =D29*(1+F28) -> 38500
A30: 财务净现值（万元） | B30: =D30*(1-17.9%) -> 160940.1 | C30: =D30*(1-9%) -> 178386.72 | D30: =D20 -> 196029.36 | E30: =D30*(1+9%) -> 213672 | F30: =D30*(1+18.2%) -> 231706.7

Sheet 能耗分析
A1: 项目综合能耗计算表
A2: 公用工程名称 | B2: 单位 | C2: 消耗 | E2: 能耗低热值或能耗指标 | G2: 单位能耗 | H2: 总能耗 | I2: 单位能耗占比
C3: 小时耗量 | D3: 年耗量 | E3: 单位 | F3: 数量 | G3: MJ/t | H3: MJ/a
A4: 三氟甲烷 | B4: t/a | C4: 4.3286102 | D4: =C4*8000 -> 34628.882 | E4: MJ/t | F4: 15.5 | G4: =H4/产品销售收入和税金估算!D7 -> 4.1170676 | H4: =D4*F4 -> 536747.67 | I4: =H4/$H$13*100 -> 0.0028260592
A5: 电 | B5: kW·h/a | C5: 7834.9984 | D5: =C5*8000 -> 62679987 | E5: MJ/kw•h | F5: 3.6 | G5: =H5/产品销售收入和税金估算!D7 -> 1730.8093 | H5: =D5*F5 -> 2.2564795e+08 | I5: =H5/$H$13*100 -> 1.1880712
A6: 0.25MPa低压蒸汽 | B6: t/a | C6: 100.15932 | D6: =C6*8000 -> 801274.59 | E6: MJ/t | F6: 2773.3 | G6: =H6/产品销售收入和税金估算!D7 -> 17044.963 | H6: =D6*F6 -> 2.2221748e+09 | I6: =H6/$H$13*100 -> 11.700093
A7: 4MPa中压蒸汽 | B7: t/a | C7: 535.29086 | D7: =C7*8000 -> 4282326.8 | E7: MJ/t | F7: 3684 | G7: =H7/产品销售收入和税金估算!D7 -> 121008.89 | H7: =D7*F7 -> 1.5776092e+10 | I7: =H7/$H$13*100 -> 83.063556
A8: 20℃冷却水 | B8: t/a | C8: 1963.3008 | D8: =C8*8000 -> 15706407 | E8: MJ/t | F8: 4.19 | G8: =H8/产品销售收入和税金估算!D7 -> 504.78762 | H8: =D8*F8 -> 65809843 | I8: =H8/$H$13*100 -> 0.34649897
A9: -25℃冷冻盐水 | B9: t/a | C9: 4.4783672 | D9: =C9*8000 -> 35826.937 | E9: MJ/t | F9: 4.01 | G9: =H9/产品销售收入和税金估算!D7 -> 1.1019754 | H9: =D9*F9 -> 143666.02 | I9: =H9/$H$13*100 -> 0.00075642373
A10: 氮气 | B10: Nm3/a | C10: 7.85 | D10: =C10*8000 -> 62800 | E10: MJ/Nm3 | F10: 11.72 | G10: =H10/产品销售收入和税金估算!D7 -> 5.6455348 | H10: =D10*F10 -> 736016 | I10: =H10/$H$13*100 -> 0.0038752377
A11: 仪表空气 | B11: Nm3/a | C11: 6 | D11: =C11*8000 -> 48000 | E11: MJ/Nm3 | F11: 1.17 | G11: =H11/产品销售收入和税金估算!D7 -> 0.43076949 | H11: =D11*F11 -> 56160 | I11: =H11/$H$13*100 -> 0.00029569106
A12: 烟道气 | B12: t/a | C12: 143.94636 | D12: =C12*8000 -> 1151570.9 | E12: MJ/t | F12: =2.0324*300 -> 609.72 | G12: =H12/产品销售收入和税金估算!D7 -> 5385.6602 | H12: =D12*F12 -> 7.0213579e+08 | I12: =H12/$H$13*100 -> 3.6968532
A13: 合计 | G13: =SUM(G5:G12) -> 145682.29 | H13: =SUM(H5:H12) -> 1.8992796e+10 | I13: =SUM(I5:I12) -> 100
H15: =SUM(H5:H6,H8:H12) -> 3.2167043e+09
C16: =2.0324*17548.1543 -> 35664.869 | F16: 燃料和烟道气关系 | H16: 一吨煤产生的烟道气质量/t | I16: 600℃以上的烟道气比热容
F17: 1吨煤=6690Nm3烟道气 | H17: =6690*0.001 -> 6.69 | I17: 2.0324 MJ/(t·℃）
A18: 每吨产品能耗计算表
A19: 公用工程名称 | B19: 单位 | C19: 消耗 | E19: 折算当量标煤系数 | G19: 单位能耗 | H19: 折算能耗
C20: 小时耗量 | D20: 年耗量 | E20: 单位 | F20: 数量 | G20: kgce/t | H20: kgce/a
A21: 三氟甲烷 | B21: t/a | C21: 4.3286102 | D21: =C21*8000 -> 34628.882 | E21: kgce/t | F21: =G36 -> 0.529 | G21: =H21/产品销售收入和税金估算!D7 -> 0.14051153 | H21: =F21*D21 -> 18318.678
A22: 电 | B22: kW·h/a | C22: 7834.9984 | D22: =C22*8000 -> 62679987 | E22: kgce/kW·h | F22: 0.1229 | G22: =H22/产品销售收入和税金估算!D7 -> 59.087908 | H22: =F22*D22 -> 7703370.4
A23: 0.25MPa低压蒸汽 | B23: t/a | C23: 100.15932 | D23: =C23*8000 -> 801274.59 | E23: kgce/t | F23: 94.63 | G23: =H23/产品销售收入和税金估算!D7 -> 581.60489 | H23: =F23*D23 -> 75824615
A24: 4MPa中压蒸汽 | B24: t/a | C24: 535.29086 | D24: =C24*8000 -> 4282326.8 | E24: kgce/t | F24: 125.7 | G24: =H24/产品销售收入和税金估算!D7 -> 4128.8863 | H24: =F24*D24 -> 5.3828848e+08
A25: 20℃冷却水 | B25: t/a | C25: 1963.3008 | D25: =C25*8000 -> 15706407 | E25: kgce/t | F25: 0.1429 | G25: =H25/产品销售收入和税金估算!D7 -> 17.215788 | H25: =F25*D25 -> 2244445.5
A26: -25℃冷冻盐水 | B26: t/a | C26: 4.4783672 | D26: =C26*8000 -> 35826.937 | E26: kgce/t | F26: 0.13853 | G26: =H26/产品销售收入和税金估算!D7 -> 0.03806899 | H26: =F26*D26 -> 4963.1056
A27: 氮气 | B27: Nm3/a | C27: 7.85 | D27: =C27*8000 -> 62800 | E27: kgce/Nm3 | F27: 0.4 | G27: =H27/产品销售收入和税金估算!D7 -> 0.19268037 | H27: =F27*D27 -> 25120
A28: 仪表空气 | B28: Nm3/a | C28: 6 | D28: =C28*8000 -> 48000 | E28: kgce/Nm3 | F28: 0.04 | G28: =H28/产品销售收入和税金估算!D7 -> 0.014727162 | H28: =F28*D28 -> 1920
A29: 烟道气 | B29: t/a | C29: 143.94636 | D29: =C29*8000 -> 1151570.9 | E29: kgce/t | F29: 20.794508 | G29: =H29/产品销售收入和税金估算!D7 -> 183.678 | H29: =F29*D29 -> 23946350
A30: 合计 | G30: =SUM(G22:G29) -> 4970.7184 | H30: =SUM(H22:H29) -> 6.4803927e+08
A33: 万元产值综合能耗计算表
A34: 公用工程名称 | B34: 单位 | C34: 消耗 | E34: 万元产值消耗 | F34: 折算当量标煤系数 | H34: 万元产值折算能耗（kgce/万元）
C35: 小时耗量 | D35: 年耗量 | F35: 单位 | G35: 数量
A36: 三氟甲烷 | B36: t/a | C36: 4.3286102 | D36: =C36*8000 -> 34628.882 | E36: =D36/财务报表!$G$48 -> 0.78213599 | F36: kgce/t | G36: 0.529 | H36: =G36*E36 -> 0.41374994
A37: 电 | B37: kW·h/a | C37: 7834.9984 | D37: =C37*8000 -> 62679987 | E37: =D37/财务报表!$G$48 -> 1415.7048 | F37: kgce/kW·h | G37: 0.1229 | H37: =G37*E37 -> 173.99012
A38: 0.25MPa低压蒸汽 | B38: t/a | C38: 100.15932 | D38: =C38*8000 -> 801274.59 | E38: =D38/财务报表!$G$48 -> 18.097775 | F38: kgce/t | G38: 94.63 | H38: =G38*E38 -> 1712.5924
A39: 4MPa中压蒸汽 | B39: t/a | C39: 535.29086 | D39: =C39*8000 -> 4282326.8 | E39: =D39/财务报表!$G$48 -> 96.721632 | F39: kgce/t | G39: 125.7 | H39: =G39*E39 -> 12157.909
A40: 20℃冷却水 | B40: t/a | C40: 1963.3008 | D40: =C40*8000 -> 15706407 | E40: =D40/财务报表!$G$48 -> 354.74856 | F40: kgce/t | G40: 0.1429 | H40: =G40*E40 -> 50.693569
A41: -25℃冷冻盐水 | B41: t/a | C41: 4.4783672 | D41: =C41*8000 -> 35826.937 | E41: =D41/财务报表!$G$48 -> 0.80919555 | F41: kgce/t | G41: 1.3853 | H41: =G41*E41 -> 1.1209786
A42: 氮气 | B42: Nm3/a | C42: 7.85 | D42: =C42*8000 -> 62800 | E42: =D42/财务报表!$G$48 -> 1.4184154 | F42: kgce/Nm3 | G42: 0.4 | H42: =G42*E42 -> 0.56736617
A43: 仪表空气 | B43: Nm3/a | C43: 6 | D43: =C43*8000 -> 48000 | E43: =D43/财务报表!$G$48 -> 1.0841392 | F43: kgce/Nm3 | G43: 0.04 | H43: =G43*E43 -> 0.043365567
A44: 烟道气 | B44: t/a | C44: 143.94636 | D44: =C44*8000 -> 1151570.9 | E44: =D44/财务报表!$G$48 -> 26.009648 | F44: kgce/t | G44: 129.577 | H44: =G44*E44 -> 3370.2522
A45: 合计 | E45: =SUM(E37:E44) -> 1914.5942 | F45: =SUM(H37:H44) -> 17467.169
